Prompter9000/PyCount.py
Prompter9000/PyEdit.py
Prompter9000/__init__.py
Prompter9000-2.5.0.dist-info/LICENSE
Prompter9000-2.5.0.dist-info/METADATA
Prompter9000-2.5.0.dist-info/WHEEL
Prompter9000-2.5.0.dist-info/top_level.txt
Prompter9000-2.5.0.dist-info/RECORD
