Metadata-Version: 2.1
Name: Prompter9000
Version: 2.5.0
Summary: C.L.I <-> G.U.I Dictionary Editor
Author-email: Randall Nagy <r.a.nagy@gmail.com>
Project-URL: Homepage, https://github.com/soft9000/Prompter9000
Project-URL: Bug Tracker, https://github.com/soft9000/Prompter9000/issues
Classifier: Programming Language :: Python :: 3
Classifier: License :: OSI Approved :: MIT License
Classifier: Operating System :: OS Independent
Requires-Python: >=3.6
License-File: LICENSE
